{
    "categories": {
        "Страны": [
            "Россия",
            "Канада",
            "Бразилия",
            "Австралия",
            "Япония",
            "Италия",
            "Египет",
            "Франция",
            "Индия",
            "Китай"
        ],
        "Животные": [
            "Лев",
            "Тигр",
            "Слон",
            "Кенгуру",
            "Дельфин",
            "Орёл",
            "Змея",
            "Панда",
            "Кит",
            "Лягушка"
        ],
        "Еда": [
            "Пицца",
            "Суши",
            "Борщ",
            "Паста",
            "Стейк",
            "Салат",
            "Хлеб",
            "Сыр",
            "Яблоко",
            "Банан"
        ],
        "Природа": [
            "Гора",
            "Озеро",
            "Лес",
            "Пустыня",
            "Водопад",
            "Река",
            "Пляж",
            "Пещера",
            "Вулкан",
            "Остров"
        ]
    }
}
